rest_framework_serializer_extensions/__init__.py
rest_framework_serializer_extensions/fields.py
rest_framework_serializer_extensions/serializers.py
rest_framework_serializer_extensions/utils.py
rest_framework_serializer_extensions/views.py
rest_framework_serializer_extensions/__pycache__/__init__.cpython-37.pyc
rest_framework_serializer_extensions/__pycache__/fields.cpython-37.pyc
rest_framework_serializer_extensions/__pycache__/serializers.cpython-37.pyc
rest_framework_serializer_extensions/__pycache__/utils.cpython-37.pyc
rest_framework_serializer_extensions/__pycache__/views.cpython-37.pyc
djangorestframework_serializer_extensions-2.0.1.dist-info/LICENSE.md
djangorestframework_serializer_extensions-2.0.1.dist-info/METADATA
djangorestframework_serializer_extensions-2.0.1.dist-info/WHEEL
djangorestframework_serializer_extensions-2.0.1.dist-info/top_level.txt
djangorestframework_serializer_extensions-2.0.1.dist-info/RECORD
