Metadata-Version: 2.1
Name: djangorestframework-serializer-extensions
Version: 2.0.1
Summary: Extensions to DRY up Django Rest Framework serializers
Home-page: https://github.com/evenicoulddoit/django-rest-framework-serializer-extensions
Author: Ian Clark
Author-email: ianclark001@gmail.com
License: BSD
Platform: UNKNOWN
Classifier: Development Status :: 2 - Pre-Alpha
Classifier: Environment :: Web Environment
Classifier: Framework :: Django
Classifier: Intended Audience :: Developers
Classifier: License :: OSI Approved :: BSD License
Classifier: Operating System :: OS Independent
Classifier: Natural Language :: English
Classifier: Programming Language :: Python :: 3
Classifier: Programming Language :: Python :: 3.6
Classifier: Programming Language :: Python :: 3.7
Classifier: Programming Language :: Python :: 3.8
Classifier: Topic :: Internet :: WWW/HTTP
Requires-Dist: hashids (>1.0.0)
